ctraceback/__init__.py
ctraceback/__main__.py
ctraceback/__version__.py
ctraceback/config.py
ctraceback/custom_traceback.py
ctraceback/on_top.py
ctraceback/server.py
ctraceback/test.py
ctraceback/traceback.ini
ctraceback/traceback.json
ctraceback/handler/__init__.py
ctraceback/handler/rabbitmq.py
ctraceback-1.16.2.data/data/LICENSE.rst
ctraceback-1.16.2.data/data/README.md
ctraceback-1.16.2.data/data/__version__.py
ctraceback-1.16.2.data/data/traceback.ini
ctraceback-1.16.2.data/data/traceback.json
ctraceback-1.16.2.dist-info/licenses/LICENSE.rst
ctraceback-1.16.2.dist-info/METADATA
ctraceback-1.16.2.dist-info/WHEEL
ctraceback-1.16.2.dist-info/entry_points.txt
ctraceback-1.16.2.dist-info/top_level.txt
ctraceback-1.16.2.dist-info/RECORD
