Metadata-Version: 2.4
Name: ctraceback
Version: 1.16.2
Summary: Custom traceback
Home-page: https://github.com/cumulus13/ctraceback
Author: Hadi Cahyadi LD
Author-email: cumulus13@gmail.com
Maintainer: cumulus13 Team
Maintainer-email: cumulus13@gmail.com
License: GPL
Project-URL: Documentation, https://github.com/cumulus13/ctraceback
Project-URL: Code, https://github.com/cumulus13/ctraceback
Classifier: Development Status :: 5 - Production/Stable
Classifier: Intended Audience :: Developers
Classifier: License :: OSI Approved :: GNU General Public License (GPL)
Classifier: Operating System :: Microsoft :: Windows
Classifier: Programming Language :: Python
Classifier: Programming Language :: Python :: 3
Requires-Python: >=3
License-File: LICENSE.rst
Requires-Dist: pygetwindow; platform_system == "Windows"
Requires-Dist: argparse
Requires-Dist: configset
Requires-Dist: rich
Requires-Dist: pydebugger
Requires-Dist: ctype; platform_system == "Windows"
Requires-Dist: pywin32; platform_system == "Windows"
Requires-Dist: psutil
Requires-Dist: pika
Requires-Dist: tenacity
Requires-Dist: amqp
Requires-Dist: kombu
Requires-Dist: richcolorlog
Dynamic: author
Dynamic: author-email
Dynamic: classifier
Dynamic: description
Dynamic: description-content-type
Dynamic: home-page
Dynamic: license
Dynamic: license-file
Dynamic: maintainer
Dynamic: maintainer-email
Dynamic: project-url
Dynamic: requires-dist
Dynamic: requires-python
Dynamic: summary
